{"url":"http://www.amazon.com/Irish-Patricks-House-Holiday-Shamrocks/dp/B018EZY6SE/ref=pd_sbs_79_6/185-5045225-9220526?ie=UTF8&dpID=515if9qlzUL&dpSrc=sims&preST=_AC_UL160_SR112%2C160_&refRID=1K17F23KKG7WQENJPQW2","name":"0_14_70","review":"Disappointed as this flag has \"ties\" to hold it to the post and not the usual \"loops\" sewn inside the sleeve :( bummer!But the quality of the flag itself is nice.","upvotes":0,"downvotes":0,"productTitle":"Luck O' The Irish St. Patrick's Day House Flag Holiday Shamrocks 28\" x 40\"","imageUrl":"http://ecx.images-amazon.com/images/I/515if9qlzUL._AC_UL160_SR112,160_.jpg"}