{"url":"http://www.amazon.com/Zone-Tech-Laptop-Eating-Steering/dp/B00LFX3BKW/ref=pd_sbs_263_4/179-9597113-6890450?ie=UTF8&dpID=51gu166efrL&dpSrc=sims&preST=_AC_UL160_SR159%2C160_&refRID=19DEBF60BSJV1SP4ZB5M","name":"3_16_39","review":"Sturdy construction. Attaches easily to steering wheel. One side has groves to hold a tablet and the other side is smooth as a writing surface. It will only hold the 12\" Surface Pro 3 at a portrait angle on the groove side.I recommend this product.","upvotes":0,"downvotes":0,"productTitle":"Zone Tech Car Ipad Laptop/Eating Steering Wheel Desk","imageUrl":"http://ecx.images-amazon.com/images/I/51gu166efrL._AC_UL160_SR159,160_.jpg"}